setup.py
hdql/__init__.py
hdql.egg-info/PKG-INFO
hdql.egg-info/SOURCES.txt
hdql.egg-info/dependency_links.txt
hdql.egg-info/top_level.txt