Metadata-Version: 1.0
Name: hdql
Version: 0.0.1
Summary: Short description
Home-page: UNKNOWN
Author: andriy_yatskovets
Author-email: UNKNOWN
License: MIT
Platform: UNKNOWN
